tests/__init__.py
tests/config_test.py
tests/parser_test.py
tests/test_file_tree.py
typeconf/__init__.py
typeconf/attribute.py
typeconf/config_template.py
typeconf/dep_graph.py
typeconf/file_tree.py
typeconf/parser.py
typeconf/type_factory.py
typeconf/utils.py
typeconf-0.1.dist-info/LICENSE
typeconf-0.1.dist-info/METADATA
typeconf-0.1.dist-info/WHEEL
typeconf-0.1.dist-info/top_level.txt
typeconf-0.1.dist-info/RECORD
