Metadata-Version: 2.1
Name: typeconf
Version: 0.1
Summary: A static configuration parser for python using templates
Home-page: https://github.com/kilsenp/TypeConf
Author: Kilian Pfeiffer
Author-email: kilian.pfeiffer@rwth-aachen.de
License: UNKNOWN
Platform: UNKNOWN
Classifier: Programming Language :: Python :: 3
Classifier: License :: OSI Approved :: MIT License
Classifier: Operating System :: OS Independent
Requires-Python: >=3.6
